pacote_texto/__init__.py
pacote_texto/analise.py
pacote_texto/limpeza.py
pacote_texto/resumo.py
pacote_texto-0.0.1.dist-info/METADATA
pacote_texto-0.0.1.dist-info/WHEEL
pacote_texto-0.0.1.dist-info/top_level.txt
pacote_texto-0.0.1.dist-info/RECORD
