Metadata-Version: 2.4
Name: pacote_texto
Version: 0.0.1
Summary: Criando pacote para fins educacionais
Author: milena
Classifier: Programming Language :: Python :: 3
Classifier: License :: OSI Approved :: MIT License
Requires-Python: >=3.6
Dynamic: author
Dynamic: classifier
Dynamic: requires-python
Dynamic: summary
